zerru/__init__.py
zerru/zerru.py
zerru-0.0.6.dist-info/LICENSE
zerru-0.0.6.dist-info/METADATA
zerru-0.0.6.dist-info/WHEEL
zerru-0.0.6.dist-info/top_level.txt
zerru-0.0.6.dist-info/RECORD
