Metadata-Version: 2.1
Name: zerru
Version: 0.0.6
Summary: Zerru — это модуль zer на русском! Для сокращения и автоматизации кода.
Author: ZerProg studio
License-File: LICENSE
Requires-Dist: tqdm
